mon_app/__init__.py
mon_app/admin.py
mon_app/apps.py
mon_app/tests.py
mon_app/urls.py
mon_app/migrations/__init__.py
mon_app/models/__init__.py
mon_app/views/__init__.py
startapp_plus/__init__.py
startapp_plus/__main__.py
startapp_plus/generator.py
startapp_plus-2.6.dist-info/licenses/LICENSE
startapp_plus-2.6.dist-info/METADATA
startapp_plus-2.6.dist-info/WHEEL
startapp_plus-2.6.dist-info/entry_points.txt
startapp_plus-2.6.dist-info/top_level.txt
startapp_plus-2.6.dist-info/RECORD
