Metadata-Version: 2.4
Name: startapp-plus
Version: 2.6
Summary: Un générateur de structure d'app Django améliorée
Author-email: prince01 <axelvianney49@gmail.com>
Classifier: Programming Language :: Python :: 3
Classifier: Framework :: Django
Requires-Python: >=3.8
License-File: LICENSE
Requires-Dist: django>=4.2
Dynamic: license-file
